{
  "_meta": {
    "base_w": 1920,
    "base_h": 1080
  },
  "seats": {
    "seat_c1r1": [
      [
        270,
        656
      ],
      [
        416,
        613
      ],
      [
        490,
        848
      ],
      [
        320,
        902
      ],
      [
        270,
        655
      ],
      [
        270,
        656
      ]
    ],
    "seat_c1r2": [
      [
        274,
        515
      ],
      [
        399,
        478
      ],
      [
        416,
        607
      ],
      [
        269,
        656
      ],
      [
        274,
        515
      ]
    ],
    "seat_c1r3": [
      [
        280,
        391
      ],
      [
        374,
        368
      ],
      [
        396,
        477
      ],
      [
        274,
        511
      ],
      [
        280,
        391
      ]
    ],
    "seat_c1r4": [
      [
        280,
        315
      ],
      [
        365,
        290
      ],
      [
        376,
        362
      ],
      [
        278,
        390
      ],
      [
        280,
        315
      ]
    ],
    "seat_c1r5": [
      [
        294,
        255
      ],
      [
        365,
        236
      ],
      [
        364,
        291
      ],
      [
        282,
        312
      ],
      [
        294,
        255
      ]
    ],
    "seat_c1r6": [
      [
        301,
        211
      ],
      [
        359,
        193
      ],
      [
        366,
        234
      ],
      [
        294,
        252
      ],
      [
        301,
        211
      ]
    ],
    "seat_c2r1": [
      [
        428,
        607
      ],
      [
        572,
        568
      ],
      [
        662,
        779
      ],
      [
        495,
        840
      ],
      [
        428,
        607
      ]
    ],
    "seat_c2r2": [
      [
        401,
        473
      ],
      [
        518,
        443
      ],
      [
        568,
        565
      ],
      [
        425,
        606
      ],
      [
        401,
        473
      ]
    ],
    "seat_c2r3": [
      [
        381,
        362
      ],
      [
        478,
        338
      ],
      [
        514,
        439
      ],
      [
        400,
        470
      ],
      [
        381,
        362
      ]
    ],
    "seat_c2r4": [
      [
        370,
        287
      ],
      [
        455,
        267
      ],
      [
        475,
        334
      ],
      [
        376,
        357
      ],
      [
        370,
        287
      ]
    ],
    "seat_c2r5": [
      [
        366,
        234
      ],
      [
        440,
        214
      ],
      [
        452,
        261
      ],
      [
        369,
        286
      ],
      [
        366,
        234
      ]
    ],
    "seat_c2r6": [
      [
        364,
        195
      ],
      [
        428,
        176
      ],
      [
        439,
        212
      ],
      [
        370,
        230
      ],
      [
        364,
        195
      ]
    ],
    "seat_c3r1": [
      [
        576,
        565
      ],
      [
        718,
        524
      ],
      [
        834,
        722
      ],
      [
        666,
        778
      ],
      [
        576,
        565
      ]
    ],
    "seat_c3r2": [
      [
        519,
        441
      ],
      [
        639,
        411
      ],
      [
        718,
        519
      ],
      [
        572,
        561
      ],
      [
        519,
        441
      ]
    ],
    "seat_c3r3": [
      [
        481,
        334
      ],
      [
        579,
        312
      ],
      [
        636,
        404
      ],
      [
        516,
        436
      ],
      [
        481,
        334
      ]
    ],
    "seat_c3r4": [
      [
        460,
        266
      ],
      [
        542,
        245
      ],
      [
        580,
        311
      ],
      [
        480,
        328
      ],
      [
        460,
        266
      ]
    ],
    "seat_c3r5": [
      [
        446,
        212
      ],
      [
        518,
        197
      ],
      [
        539,
        242
      ],
      [
        461,
        260
      ],
      [
        446,
        212
      ]
    ],
    "seat_c3r6": [
      [
        434,
        177
      ],
      [
        498,
        163
      ],
      [
        516,
        195
      ],
      [
        442,
        208
      ],
      [
        434,
        177
      ]
    ],
    "seat_c4r1": [
      [
        814,
        379
      ],
      [
        939,
        353
      ],
      [
        1029,
        553
      ],
      [
        879,
        590
      ],
      [
        814,
        379
      ]
    ],
    "seat_c4r2": [
      [
        751,
        290
      ],
      [
        849,
        266
      ],
      [
        938,
        351
      ],
      [
        810,
        379
      ],
      [
        751,
        290
      ]
    ],
    "seat_c4r3": [
      [
        685,
        221
      ],
      [
        779,
        206
      ],
      [
        848,
        264
      ],
      [
        744,
        290
      ],
      [
        685,
        221
      ]
    ],
    "seat_c4r4": [
      [
        638,
        185
      ],
      [
        720,
        166
      ],
      [
        775,
        204
      ],
      [
        671,
        226
      ],
      [
        638,
        185
      ]
    ],
    "seat_c4r5": [
      [
        599,
        148
      ],
      [
        679,
        127
      ],
      [
        720,
        165
      ],
      [
        638,
        187
      ],
      [
        599,
        148
      ]
    ],
    "seat_c4r6": [
      [
        572,
        117
      ],
      [
        639,
        106
      ],
      [
        658,
        132
      ],
      [
        596,
        148
      ],
      [
        572,
        117
      ]
    ],
    "seat_c5r1": [
      [
        944,
        350
      ],
      [
        1034,
        334
      ],
      [
        1119,
        508
      ],
      [
        1029,
        545
      ],
      [
        944,
        350
      ]
    ],
    "seat_c5r2": [
      [
        851,
        266
      ],
      [
        938,
        253
      ],
      [
        948,
        285
      ],
      [
        1030,
        334
      ],
      [
        938,
        350
      ],
      [
        851,
        266
      ]
    ],
    "seat_c5r3": [
      [
        779,
        207
      ],
      [
        858,
        195
      ],
      [
        869,
        229
      ],
      [
        932,
        248
      ],
      [
        849,
        259
      ],
      [
        779,
        207
      ]
    ],
    "seat_c5r4": [
      [
        726,
        159
      ],
      [
        791,
        155
      ],
      [
        812,
        181
      ],
      [
        851,
        192
      ],
      [
        780,
        204
      ],
      [
        726,
        159
      ]
    ],
    "seat_c5r5": [
      [
        690,
        128
      ],
      [
        740,
        123
      ],
      [
        746,
        144
      ],
      [
        784,
        153
      ],
      [
        716,
        162
      ],
      [
        690,
        128
      ]
    ],
    "seat_c5r6": [
      [
        644,
        109
      ],
      [
        691,
        102
      ],
      [
        706,
        123
      ],
      [
        660,
        129
      ],
      [
        644,
        109
      ]
    ],
    "seat_c6r1": [
      [
        1034,
        331
      ],
      [
        1115,
        317
      ],
      [
        1215,
        463
      ],
      [
        1120,
        503
      ],
      [
        1034,
        331
      ]
    ],
    "seat_c6r2": [
      [
        940,
        251
      ],
      [
        1016,
        244
      ],
      [
        1022,
        274
      ],
      [
        1111,
        311
      ],
      [
        1026,
        330
      ],
      [
        960,
        293
      ],
      [
        940,
        251
      ]
    ],
    "seat_c6r3": [
      [
        860,
        196
      ],
      [
        928,
        191
      ],
      [
        932,
        212
      ],
      [
        1011,
        242
      ],
      [
        929,
        253
      ],
      [
        874,
        227
      ],
      [
        860,
        196
      ]
    ],
    "seat_c6r4": [
      [
        794,
        154
      ],
      [
        854,
        150
      ],
      [
        866,
        172
      ],
      [
        924,
        188
      ],
      [
        859,
        192
      ],
      [
        812,
        181
      ],
      [
        794,
        154
      ]
    ],
    "seat_c6r5": [
      [
        742,
        123
      ],
      [
        798,
        117
      ],
      [
        805,
        136
      ],
      [
        849,
        148
      ],
      [
        792,
        154
      ],
      [
        749,
        143
      ],
      [
        742,
        123
      ]
    ],
    "seat_c6r6": [
      [
        695,
        101
      ],
      [
        745,
        93
      ],
      [
        751,
        104
      ],
      [
        789,
        116
      ],
      [
        710,
        127
      ],
      [
        695,
        101
      ]
    ],
    "seat_c7r1": [
      [
        1125,
        316
      ],
      [
        1185,
        306
      ],
      [
        1272,
        436
      ],
      [
        1216,
        463
      ],
      [
        1125,
        316
      ]
    ],
    "seat_c7r2": [
      [
        1016,
        241
      ],
      [
        1082,
        232
      ],
      [
        1096,
        268
      ],
      [
        1179,
        305
      ],
      [
        1108,
        315
      ],
      [
        1029,
        275
      ],
      [
        1016,
        241
      ]
    ],
    "seat_c7r3": [
      [
        931,
        185
      ],
      [
        998,
        178
      ],
      [
        1004,
        211
      ],
      [
        1068,
        232
      ],
      [
        1005,
        242
      ],
      [
        932,
        212
      ],
      [
        931,
        185
      ]
    ],
    "seat_c7r4": [
      [
        855,
        146
      ],
      [
        916,
        140
      ],
      [
        925,
        165
      ],
      [
        981,
        180
      ],
      [
        922,
        188
      ],
      [
        872,
        176
      ],
      [
        855,
        146
      ]
    ],
    "seat_c7r5": [
      [
        799,
        117
      ],
      [
        862,
        106
      ],
      [
        865,
        129
      ],
      [
        910,
        136
      ],
      [
        855,
        146
      ],
      [
        809,
        140
      ],
      [
        799,
        117
      ]
    ],
    "seat_c7r6": [
      [
        750,
        93
      ],
      [
        814,
        84
      ],
      [
        854,
        106
      ],
      [
        788,
        118
      ],
      [
        756,
        106
      ],
      [
        751,
        95
      ],
      [
        750,
        93
      ]
    ],
    "seat_c8r1": [
      [
        1416,
        493
      ],
      [
        1424,
        362
      ],
      [
        1468,
        347
      ],
      [
        1485,
        387
      ],
      [
        1561,
        449
      ],
      [
        1516,
        547
      ],
      [
        1416,
        493
      ]
    ],
    "seat_c8r2": [
      [
        1295,
        294
      ],
      [
        1344,
        286
      ],
      [
        1359,
        320
      ],
      [
        1416,
        361
      ],
      [
        1399,
        464
      ],
      [
        1298,
        418
      ],
      [
        1295,
        294
      ]
    ],
    "seat_c8r3": [
      [
        1189,
        226
      ],
      [
        1241,
        226
      ],
      [
        1252,
        260
      ],
      [
        1304,
        289
      ],
      [
        1281,
        384
      ],
      [
        1208,
        325
      ],
      [
        1189,
        226
      ]
    ],
    "seat_c8r4": [
      [
        1102,
        184
      ],
      [
        1150,
        176
      ],
      [
        1159,
        200
      ],
      [
        1212,
        219
      ],
      [
        1182,
        225
      ],
      [
        1185,
        294
      ],
      [
        1119,
        267
      ],
      [
        1102,
        184
      ]
    ],
    "seat_c8r5": [
      [
        1016,
        139
      ],
      [
        1070,
        136
      ],
      [
        1111,
        180
      ],
      [
        1089,
        240
      ],
      [
        1031,
        212
      ],
      [
        1016,
        139
      ]
    ],
    "seat_c8r6": [
      [
        958,
        104
      ],
      [
        1005,
        102
      ],
      [
        1030,
        192
      ],
      [
        966,
        162
      ],
      [
        958,
        104
      ]
    ],
    "seat_c9r1": [
      [
        1470,
        343
      ],
      [
        1508,
        336
      ],
      [
        1524,
        372
      ],
      [
        1582,
        403
      ],
      [
        1564,
        452
      ],
      [
        1499,
        402
      ],
      [
        1470,
        343
      ]
    ],
    "seat_c9r2": [
      [
        1349,
        287
      ],
      [
        1390,
        278
      ],
      [
        1396,
        311
      ],
      [
        1465,
        340
      ],
      [
        1420,
        358
      ],
      [
        1368,
        330
      ],
      [
        1349,
        287
      ]
    ],
    "seat_c9r3": [
      [
        1242,
        226
      ],
      [
        1286,
        217
      ],
      [
        1296,
        247
      ],
      [
        1369,
        282
      ],
      [
        1301,
        294
      ],
      [
        1254,
        266
      ],
      [
        1242,
        226
      ]
    ],
    "seat_c9r4": [
      [
        1154,
        177
      ],
      [
        1198,
        169
      ],
      [
        1205,
        193
      ],
      [
        1265,
        219
      ],
      [
        1211,
        222
      ],
      [
        1168,
        203
      ],
      [
        1154,
        177
      ]
    ],
    "seat_c9r5": [
      [
        1079,
        138
      ],
      [
        1119,
        131
      ],
      [
        1125,
        155
      ],
      [
        1170,
        168
      ],
      [
        1111,
        180
      ],
      [
        1079,
        138
      ]
    ],
    "seat_c9r6": [
      [
        1010,
        104
      ],
      [
        1054,
        98
      ],
      [
        1060,
        117
      ],
      [
        1101,
        128
      ],
      [
        1021,
        138
      ],
      [
        1010,
        104
      ]
    ],
    "seat_c10r1": [
      [
        1510,
        339
      ],
      [
        1538,
        325
      ],
      [
        1551,
        353
      ],
      [
        1604,
        384
      ],
      [
        1584,
        404
      ],
      [
        1522,
        379
      ],
      [
        1510,
        339
      ]
    ],
    "seat_c10r2": [
      [
        1392,
        276
      ],
      [
        1432,
        271
      ],
      [
        1509,
        332
      ],
      [
        1474,
        339
      ],
      [
        1414,
        316
      ],
      [
        1392,
        276
      ]
    ],
    "seat_c10r3": [
      [
        1290,
        219
      ],
      [
        1340,
        210
      ],
      [
        1425,
        268
      ],
      [
        1366,
        274
      ],
      [
        1310,
        251
      ],
      [
        1290,
        219
      ]
    ],
    "seat_c10r4": [
      [
        1208,
        168
      ],
      [
        1251,
        166
      ],
      [
        1316,
        210
      ],
      [
        1261,
        217
      ],
      [
        1216,
        195
      ],
      [
        1208,
        168
      ]
    ],
    "seat_c10r5": [
      [
        1119,
        133
      ],
      [
        1181,
        125
      ],
      [
        1239,
        162
      ],
      [
        1172,
        173
      ],
      [
        1129,
        154
      ],
      [
        1119,
        133
      ]
    ],
    "seat_c10r6": [
      [
        1056,
        102
      ],
      [
        1114,
        101
      ],
      [
        1151,
        121
      ],
      [
        1100,
        129
      ],
      [
        1065,
        118
      ],
      [
        1056,
        102
      ]
    ]
  }
}